mypackage/__init__.py
mypackage/utils.py
mypackage_demo_tutorial_2024-0.1.0.dist-info/licenses/LICENSE
mypackage_demo_tutorial_2024-0.1.0.dist-info/METADATA
mypackage_demo_tutorial_2024-0.1.0.dist-info/WHEEL
mypackage_demo_tutorial_2024-0.1.0.dist-info/top_level.txt
mypackage_demo_tutorial_2024-0.1.0.dist-info/RECORD
