Metadata-Version: 2.4
Name: mypackage-demo-tutorial-2024
Version: 0.1.0
Summary: 一个简单的Python库示例，提供基本数学工具函数
Author-email: Your Name <your.email@example.com>
License: MIT
Project-URL: Homepage, https://github.com/yourusername/mypackage-example
Project-URL: Bug Tracker, https://github.com/yourusername/mypackage-example/issues
Keywords: math,utility,example
Classifier: Development Status :: 3 - Alpha
Classifier: Intended Audience :: Developers
Classifier: License :: OSI Approved :: MIT License
Classifier: Operating System :: OS Independent
Classifier: Programming Language :: Python :: 3
Classifier: Programming Language :: Python :: 3.7
Classifier: Programming Language :: Python :: 3.8
Classifier: Programming Language :: Python :: 3.9
Classifier: Programming Language :: Python :: 3.10
Classifier: Programming Language :: Python :: 3.11
Requires-Python: >=3.7
License-File: LICENSE
Requires-Dist: build>=1.1.1
Requires-Dist: twine>=4.0.2
Dynamic: license-file
